nwb2bids/__init__.py
nwb2bids/_hidden_top_level_imports.py
nwb2bids/_command_line_interface/__init__.py
nwb2bids/_command_line_interface/_main.py
nwb2bids/_converters/__init__.py
nwb2bids/_converters/_base_converter.py
nwb2bids/_converters/_dandi_utils.py
nwb2bids/_converters/_datalad_utils.py
nwb2bids/_converters/_dataset_converter.py
nwb2bids/_converters/_run_config.py
nwb2bids/_converters/_session_converter.py
nwb2bids/_core/__init__.py
nwb2bids/_core/_convert_nwb_dataset.py
nwb2bids/_core/_file_mode.py
nwb2bids/_core/_home.py
nwb2bids/_core/_validate_existing_bids.py
nwb2bids/_tools/__init__.py
nwb2bids/_tools/_cache_nwb.py
nwb2bids/_tools/_pluralize.py
nwb2bids/bids_models/__init__.py
nwb2bids/bids_models/_base_metadata_model.py
nwb2bids/bids_models/_bids_session_metadata.py
nwb2bids/bids_models/_channels.py
nwb2bids/bids_models/_dataset_description.py
nwb2bids/bids_models/_electrodes.py
nwb2bids/bids_models/_events.py
nwb2bids/bids_models/_general_metadata.py
nwb2bids/bids_models/_model_globals.py
nwb2bids/bids_models/_participant.py
nwb2bids/bids_models/_probes.py
nwb2bids/notifications/__init__.py
nwb2bids/notifications/_notification.py
nwb2bids/notifications/_registry.py
nwb2bids/sanitization/__init__.py
nwb2bids/sanitization/_configuration.py
nwb2bids/sanitization/_sanitization.py
nwb2bids/testing/__init__.py
nwb2bids/testing/_assert_subdirectory_structure.py
nwb2bids/testing/_create_file_tree.py
nwb2bids/testing/_mocks/__init__.py
nwb2bids/testing/_mocks/_mock_neurodata_objects.py
nwb2bids/testing/_mocks/_tutorials.py
nwb2bids-0.9.0.dist-info/METADATA
nwb2bids-0.9.0.dist-info/WHEEL
nwb2bids-0.9.0.dist-info/entry_points.txt
nwb2bids-0.9.0.dist-info/licenses/LICENSE.txt
nwb2bids-0.9.0.dist-info/RECORD
