Metadata-Version: 2.4
Name: nwb2bids
Version: 0.9.0
Summary: Reorganize NWB files into a BIDS directory layout.
Project-URL: Repository, https://github.com/con/nwb2bids/
Project-URL: Issues, https://github.com/con/nwb2bids/issues
Project-URL: Changelog, https://github.com/con/nwb2bids/blob/main/CHANGELOG.md
Author-email: Cody Baker <cody.c.baker.phd@gmail.com>
License: MIT License
License-File: LICENSE.txt
Keywords: BIDS,Brain Imaging Data Structure,DANDI Archive,NWB,NeurodataWithoutBorders,data organization,data standards,neurodata,neuroscience
Classifier: Development Status :: 4 - Beta
Classifier: Intended Audience :: Developers
Classifier: Intended Audience :: Science/Research
Classifier: License :: OSI Approved :: MIT License
Classifier: Operating System :: MacOS
Classifier: Operating System :: Microsoft :: Windows
Classifier: Operating System :: Unix
Classifier: Programming Language :: Python
Classifier: Programming Language :: Python :: 3.10
Classifier: Programming Language :: Python :: 3.11
Classifier: Programming Language :: Python :: 3.12
Classifier: Programming Language :: Python :: 3.13
Classifier: Topic :: Scientific/Engineering :: Information Analysis
Requires-Python: >=3.10
Requires-Dist: pandas
Requires-Dist: pydantic
Requires-Dist: pynwb
Requires-Dist: rich-click
Requires-Dist: ruamel-yaml~=0.18.15
Requires-Dist: typing-extensions
Provides-Extra: all
Requires-Dist: dandi; extra == 'all'
Requires-Dist: remfile; extra == 'all'
Provides-Extra: dandi
Requires-Dist: dandi; extra == 'dandi'
Requires-Dist: remfile; extra == 'dandi'
